infantnetwork/ComputeNetworkMetrics_old.py
infantnetwork/__init__.py
infantnetwork/computeNetwork.py
infantnetwork/network_parameters_and_data.py
infantnetwork/tests/__init__.py
infantnetwork/tests/test_computeNetwork.py
infantnetwork-0.1.2.dist-info/LICENSE
infantnetwork-0.1.2.dist-info/METADATA
infantnetwork-0.1.2.dist-info/WHEEL
infantnetwork-0.1.2.dist-info/top_level.txt
infantnetwork-0.1.2.dist-info/RECORD
