Metadata-Version: 2.1
Name: infantnetwork
Version: 0.1.2
Summary: Python package to construct and describe neonatal transfer networks.
Author-email: Daniel Helkey <dhelkey@stanford.edu>, Marinka Zitnik <marinka@hms.harvard.edu>
Project-URL: Homepage, https://github.com/dhelkey/infantnetwork
Project-URL: Bug Tracker, https://github.com/dhelkey/infantnetwork/issues
Classifier: Programming Language :: Python :: 3
Classifier: License :: OSI Approved :: MIT License
Classifier: Operating System :: OS Independent
Requires-Python: >=3.6
License-File: LICENSE
Requires-Dist: numpy
Requires-Dist: scipy
Requires-Dist: igraph
Requires-Dist: networkx
